{
  "results": [
    {
      "fmParamsList": {
        "operator1": {
          "attack": 362.902296158737,
          "decay": 143.35898771084914,
          "sustain": 208.5670117156258,
          "sustainTime": 241.86876412567386,
          "release": 305.2911666482951,
          "frequency": 43.704278906038354
        }
      },
      "fitness": 2.388508880744784,
      "pre_evaluation": 1.8563713123038403,
      "generation": 9,
      "chromosomeId": "65b3404e-7457-4741-aea2-b1aa7043f4eb"
    },
    {
      "fmParamsList": {
        "operator1": {
          "attack": 414.55328228975515,
          "decay": 422.9455670895583,
          "sustain": 318.2818673782048,
          "sustainTime": 132.29100310149585,
          "release": 500,
          "frequency": 415.01602917015265
        }
      },
      "fitness": 2.388508880744784,
      "pre_evaluation": 1.8563713120618857,
      "generation": 9,
      "chromosomeId": "5e2ed386-e88a-486a-9c2f-47d249de1643"
    },
    {
      "fmParamsList": {
        "operator1": {
          "attack": 107.68765781660046,
          "decay": 283.88331773187303,
          "sustain": 272.25047164441037,
          "sustainTime": 251.32813305228768,
          "release": 500,
          "frequency": 342.3183576800697
        }
      },
      "fitness": 2.388508880744784,
      "pre_evaluation": 1.85637132621014,
      "generation": 9,
      "chromosomeId": "8f8f974d-1fd2-4716-9cb4-704279cf63b0"
    },
    {
      "fmParamsList": {
        "operator1": {
          "attack": 154.0107856112012,
          "decay": 256.7016773983357,
          "sustain": 249.15412487573067,
          "sustainTime": 260.5703396106084,
          "release": 67.67658398850787,
          "frequency": 102.49671454883931
        }
      },
      "fitness": 2.388508880744784,
      "pre_evaluation": 1.8563713122504764,
      "generation": 9,
      "chromosomeId": "95048bf9-1a47-482c-9b16-a65afef7515f"
    },
    {
      "fmParamsList": {
        "operator1": {
          "attack": 235.6624690208094,
          "decay": 232.82274662467267,
          "sustain": 280.1798278758899,
          "sustainTime": 213.0939931030486,
          "release": 134.35396125278032,
          "frequency": 274.3806672241151
        }
      },
      "fitness": 2.388638319236931,
      "pre_evaluation": 1.8563713120618892,
      "generation": 9,
      "chromosomeId": "89b3a127-d0b8-499b-80d6-8e1572e26bb3"
    },
    {
      "fmParamsList": {
        "operator1": {
          "attack": 457.5157616562575,
          "decay": 79.91763939752151,
          "sustain": 291.29476277005796,
          "sustainTime": 322.1785926873204,
          "release": 372.573960238065,
          "frequency": 269.2152923009746
        }
      },
      "fitness": 2.388508880744784,
      "pre_evaluation": 1.85637131206269,
      "generation": 9,
      "chromosomeId": "9869254f-ade7-4f33-846b-0451ae341813"
    },
    {
      "fmParamsList": {
        "operator1": {
          "attack": 304.72285518940544,
          "decay": 308.388482425938,
          "sustain": 376.5697978390977,
          "sustainTime": 143.99627724048565,
          "release": 93.842677480536,
          "frequency": 171.91797400317728
        }
      },
      "fitness": 2.388508880744784,
      "pre_evaluation": 1.8563713120618857,
      "generation": 9,
      "chromosomeId": "9c8b881c-4a80-4bd5-948b-3efe2976fffa"
    },
    {
      "fmParamsList": {
        "operator1": {
          "attack": 324.5469999328605,
          "decay": 286.9558571176546,
          "sustain": 81.86243652205741,
          "sustainTime": 33.965040785714706,
          "release": 461.0094499457358,
          "frequency": 136.60995345462027
        }
      },
      "fitness": 2.388508880744784,
      "pre_evaluation": 1.8563713120618857,
      "generation": 9,
      "chromosomeId": "504b13a5-ade8-4fd7-b222-c54adab5b48f"
    },
    {
      "fmParamsList": {
        "operator1": {
          "attack": 422.82914427358276,
          "decay": 346.22635337501987,
          "sustain": 338.1859752494928,
          "sustainTime": 281.3740846160642,
          "release": 500,
          "frequency": 286.054915147566
        }
      },
      "fitness": 2.388508880744784,
      "pre_evaluation": 1.8563713128104355,
      "generation": 9,
      "chromosomeId": "3d47fd2c-8f15-410e-9a5e-84ee957b6874"
    },
    {
      "fmParamsList": {
        "operator1": {
          "attack": 64.41591576234632,
          "decay": 233.40098183052422,
          "sustain": 56.52173996662295,
          "sustainTime": 236.77845726306492,
          "release": 336.12591173027783,
          "frequency": 223.58225709882478
        }
      },
      "fitness": 2.3885206011602613,
      "pre_evaluation": 1.8563713120635967,
      "generation": 9,
      "chromosomeId": "0da289e5-8b48-4ad3-97ed-72231f7e3bd6"
    },
    {
      "fmParamsList": {
        "operator1": {
          "attack": 109.3004375116877,
          "decay": 500,
          "sustain": 287.04683180948126,
          "sustainTime": 365.05781866142297,
          "release": 363.73164677658724,
          "frequency": 264.8574750342066
        }
      },
      "fitness": 2.388508880744784,
      "pre_evaluation": 1.8563713120618857,
      "generation": 9,
      "chromosomeId": "d782c971-de21-4114-934a-8e364f6f8558"
    },
    {
      "fmParamsList": {
        "operator1": {
          "attack": 85.26020148087822,
          "decay": 270.67579412746426,
          "sustain": 233.9836614292997,
          "sustainTime": 268.393128121086,
          "release": 391.64948610015864,
          "frequency": 274.81215491930715
        }
      },
      "fitness": 2.388508880744784,
      "pre_evaluation": 1.8628235583082486,
      "generation": 9,
      "chromosomeId": "ccbe5e4c-b887-4d8f-a567-4ed1c7887cb9"
    },
    {
      "fmParamsList": {
        "operator1": {
          "attack": 349.96056385518517,
          "decay": 261.7779220854625,
          "sustain": 247.7290417188894,
          "sustainTime": 51.43402351931515,
          "release": 433.28917757507617,
          "frequency": 230.5787907988849
        }
      },
      "fitness": 2.388508880744784,
      "pre_evaluation": 1.8563713120618857,
      "generation": 9,
      "chromosomeId": "87fb5e8c-4bee-481f-962a-7241825d1be6"
    },
    {
      "fmParamsList": {
        "operator1": {
          "attack": 336.0125518985448,
          "decay": 244.06555890827588,
          "sustain": 314.44912941031873,
          "sustainTime": 335.8963528768696,
          "release": 452.6567801741861,
          "frequency": 254.64122989246692
        }
      },
      "fitness": 2.388964865560841,
      "pre_evaluation": 1.8563713120618952,
      "generation": 9,
      "chromosomeId": "e0147694-f228-43dd-b092-6c6ebcd576ba"
    },
    {
      "fmParamsList": {
        "operator1": {
          "attack": 327.7538636485375,
          "decay": 234.72217024715846,
          "sustain": 324.6040577031255,
          "sustainTime": 328.75459351505435,
          "release": 184.01310584666575,
          "frequency": 173.64295008362933
        }
      },
      "fitness": 2.389178520482483,
      "pre_evaluation": 1.8563713120796879,
      "generation": 9,
      "chromosomeId": "fdd59568-a3fb-41c8-a7e0-0cd0d73faf66"
    },
    {
      "fmParamsList": {
        "operator1": {
          "attack": 254.7502862637218,
          "decay": 276.85776711967594,
          "sustain": 336.6196184968888,
          "sustainTime": 178.3958191750623,
          "release": 500,
          "frequency": 433.81265264188926
        }
      },
      "fitness": 2.388508880744784,
      "pre_evaluation": 1.8563713120618857,
      "generation": 9,
      "chromosomeId": "e61f12b4-a36e-44a4-9d50-28140f606535"
    },
    {
      "fmParamsList": {
        "operator1": {
          "attack": 263.63187774564705,
          "decay": 351.24633531775584,
          "sustain": 277.6154235864624,
          "sustainTime": 180.62151962340494,
          "release": 329.1309121551256,
          "frequency": 412.50278898147235
        }
      },
      "fitness": 2.388508880744784,
      "pre_evaluation": 1.8563713120618857,
      "generation": 9,
      "chromosomeId": "9f0209b0-fb36-437b-8ce7-28ca4d6f1c2d"
    },
    {
      "fmParamsList": {
        "operator1": {
          "attack": 500,
          "decay": 453.8708281984017,
          "sustain": 271.98045176126993,
          "sustainTime": 102.34662533417142,
          "release": 281.504432978178,
          "frequency": 4.794107994001024
        }
      },
      "fitness": 2.388508880744784,
      "pre_evaluation": 1.8563713120618857,
      "generation": 9,
      "chromosomeId": "35028a43-b685-4442-b982-d9922d1258c2"
    },
    {
      "fmParamsList": {
        "operator1": {
          "attack": 486.64763672997947,
          "decay": 272.6723824526175,
          "sustain": 0,
          "sustainTime": 457.44124819087995,
          "release": 239.1696817579969,
          "frequency": 297.11813402018913
        }
      },
      "fitness": 2.388508880744784,
      "pre_evaluation": 1.8563713120618857,
      "generation": 9,
      "chromosomeId": "763d67dc-674c-4d32-8799-a19ab7fc5609"
    },
    {
      "fmParamsList": {
        "operator1": {
          "attack": 466.74130769635167,
          "decay": 213.17398762994844,
          "sustain": 297.7323143059642,
          "sustainTime": 180.64543920517687,
          "release": 166.4634267220854,
          "frequency": 270.5756860898988
        }
      },
      "fitness": 2.388508880744784,
      "pre_evaluation": 1.8563713120618857,
      "generation": 9,
      "chromosomeId": "785d7d4e-1e83-4628-99fe-4db3dd0c49b3"
    },
    {
      "fmParamsList": {
        "operator1": {
          "attack": 413.7742179318067,
          "decay": 246.66899973330362,
          "sustain": 334.2249036220055,
          "sustainTime": 208.85497500425265,
          "release": 115.36689223886911,
          "frequency": 301.95586956956305
        }
      },
      "fitness": 2.388508881552988,
      "pre_evaluation": 1.8563713120618857,
      "generation": 9,
      "chromosomeId": "4a214543-92aa-494b-a318-6056c4db079f"
    },
    {
      "fmParamsList": {
        "operator1": {
          "attack": 426.8280174410644,
          "decay": 301.64714430979916,
          "sustain": 339.0122100693168,
          "sustainTime": 289.20790155273744,
          "release": 234.8872292070591,
          "frequency": 411.3492849438802
        }
      },
      "fitness": 2.388508880744784,
      "pre_evaluation": 1.8563721164348124,
      "generation": 9,
      "chromosomeId": "2154d424-05e9-440b-b439-3065a81e6a56"
    },
    {
      "fmParamsList": {
        "operator1": {
          "attack": 143.87691958563397,
          "decay": 275.48911635749334,
          "sustain": 292.1963201021397,
          "sustainTime": 252.79573410141657,
          "release": 432.63867537600674,
          "frequency": 220.718980900427
        }
      },
      "fitness": 2.388508880744784,
      "pre_evaluation": 1.8565488365622238,
      "generation": 9,
      "chromosomeId": "7ec58753-17fb-4bb3-9c7f-c36abb6fee0d"
    },
    {
      "fmParamsList": {
        "operator1": {
          "attack": 136.726110369546,
          "decay": 352.8370248867123,
          "sustain": 329.18350932264633,
          "sustainTime": 284.0810529781219,
          "release": 423.1771169779204,
          "frequency": 230.20047505854473
        }
      },
      "fitness": 2.388508880744784,
      "pre_evaluation": 1.8616851816308047,
      "generation": 9,
      "chromosomeId": "9ec9199b-3808-49f1-b002-2d1493792e7e"
    },
    {
      "fmParamsList": {
        "operator1": {
          "attack": 111.11519770660871,
          "decay": 226.0320002426438,
          "sustain": 245.82480133681145,
          "sustainTime": 303.4125332944965,
          "release": 407.92198539061854,
          "frequency": 488.6235114926724
        }
      },
      "fitness": 2.388508880744784,
      "pre_evaluation": 1.8563713263092152,
      "generation": 9,
      "chromosomeId": "5312b1a9-b245-46de-8c81-eab0dc6db844"
    },
    {
      "fmParamsList": {
        "operator1": {
          "attack": 66.84051478579777,
          "decay": 303.23918193800733,
          "sustain": 356.51442608724295,
          "sustainTime": 268.092432505155,
          "release": 430.30832351035076,
          "frequency": 315.0100947434824
        }
      },
      "fitness": 2.388508880744784,
      "pre_evaluation": 1.8569007310335672,
      "generation": 9,
      "chromosomeId": "5f988d2a-8917-4701-be44-e61b7039a9ba"
    },
    {
      "fmParamsList": {
        "operator1": {
          "attack": 288.2447318578619,
          "decay": 273.83863021011433,
          "sustain": 112.00357921331963,
          "sustainTime": 287.5609562906339,
          "release": 197.2661483641509,
          "frequency": 0
        }
      },
      "fitness": 2.388508880744784,
      "pre_evaluation": 1.8563713120761904,
      "generation": 9,
      "chromosomeId": "b506b773-c2fb-47ed-a164-cd1c6e708224"
    },
    {
      "fmParamsList": {
        "operator1": {
          "attack": 479.7003233320454,
          "decay": 235.333217462237,
          "sustain": 367.3745228211906,
          "sustainTime": 430.0301498076037,
          "release": 461.3319928973556,
          "frequency": 476.2132288695051
        }
      },
      "fitness": 2.388508880744784,
      "pre_evaluation": 1.8563713120618857,
      "generation": 9,
      "chromosomeId": "cb592236-03b1-40fa-aef1-a7976a30fb61"
    },
    {
      "fmParamsList": {
        "operator1": {
          "attack": 250.29119397348435,
          "decay": 473.4510264407688,
          "sustain": 368.7242813391024,
          "sustainTime": 412.52898540775584,
          "release": 223.97197592170355,
          "frequency": 264.70469103865867
        }
      },
      "fitness": 2.388508880744784,
      "pre_evaluation": 1.8563713120618857,
      "generation": 9,
      "chromosomeId": "604a11ae-ad20-4ad8-8a3b-96baa35bc070"
    },
    {
      "fmParamsList": {
        "operator1": {
          "attack": 320.87539125066604,
          "decay": 252.1469651477498,
          "sustain": 212.94499989751378,
          "sustainTime": 323.13690647457867,
          "release": 330.8985660579913,
          "frequency": 277.5462448604367
        }
      },
      "fitness": 2.3885088809127124,
      "pre_evaluation": 1.85637131916021,
      "generation": 9,
      "chromosomeId": "ed0f6f97-c31d-44f6-a65b-25298b61ba21"
    },
    {
      "fmParamsList": {
        "operator1": {
          "attack": 201.703423821085,
          "decay": 500,
          "sustain": 210.77547293983042,
          "sustainTime": 261.4956085066285,
          "release": 404.8416465177787,
          "frequency": 230.48471426229594
        }
      },
      "fitness": 2.388508880744784,
      "pre_evaluation": 1.8563898504622989,
      "generation": 9,
      "chromosomeId": "fa443af2-664f-4adc-80b1-739689ac0461"
    },
    {
      "fmParamsList": {
        "operator1": {
          "attack": 192.34407603771336,
          "decay": 228.98078386646552,
          "sustain": 277.2934704643161,
          "sustainTime": 193.23528604844702,
          "release": 364.6540611514,
          "frequency": 347.82705916330684
        }
      },
      "fitness": 2.3885088807455825,
      "pre_evaluation": 1.8563713120618857,
      "generation": 9,
      "chromosomeId": "5ed26751-3ef6-46cc-9dad-40ab9aa0d7ee"
    },
    {
      "fmParamsList": {
        "operator1": {
          "attack": 147.7201150240095,
          "decay": 429.5468164145023,
          "sustain": 500,
          "sustainTime": 243.954377335187,
          "release": 185.12444860238918,
          "frequency": 212.5277158543909
        }
      },
      "fitness": 2.388508880744784,
      "pre_evaluation": 1.8563713149345522,
      "generation": 9,
      "chromosomeId": "be9ea362-b6d9-47b4-adf3-24d47f63b847"
    },
    {
      "fmParamsList": {
        "operator1": {
          "attack": 130.68873753049436,
          "decay": 214.81460459425645,
          "sustain": 294.48591876678495,
          "sustainTime": 444.0366601671053,
          "release": 175.51939493883393,
          "frequency": 263.5877901890703
        }
      },
      "fitness": 2.388508880744784,
      "pre_evaluation": 1.8563713120618857,
      "generation": 9,
      "chromosomeId": "ff664c10-c934-4406-bfa4-7ae7c87591f8"
    },
    {
      "fmParamsList": {
        "operator1": {
          "attack": 190.01205909531862,
          "decay": 249.45973265751053,
          "sustain": 325.4759685753768,
          "sustainTime": 269.1657055691412,
          "release": 314.11490536852943,
          "frequency": 269.1709400951681
        }
      },
      "fitness": 2.388509133581792,
      "pre_evaluation": 3.179489308942254,
      "generation": 9,
      "chromosomeId": "4d24425f-3dd5-4d51-88dd-1565c33cd8da"
    },
    {
      "fmParamsList": {
        "operator1": {
          "attack": 67.84573747009898,
          "decay": 63.11783835150144,
          "sustain": 265.2081686604437,
          "sustainTime": 205.47180159541514,
          "release": 148.86798220802473,
          "frequency": 292.2028584561099
        }
      },
      "fitness": 2.388508880744784,
      "pre_evaluation": 1.8563713120618857,
      "generation": 9,
      "chromosomeId": "9c244c4f-a973-4f3c-ad21-0e280feb770f"
    },
    {
      "fmParamsList": {
        "operator1": {
          "attack": 329.3712532463487,
          "decay": 261.3310295221627,
          "sustain": 444.4434008294406,
          "sustainTime": 327.9011604605923,
          "release": 347.8322698739773,
          "frequency": 236.06155036818188
        }
      },
      "fitness": 2.388508880744784,
      "pre_evaluation": 1.8563713121225518,
      "generation": 9,
      "chromosomeId": "65082962-893c-4acb-9483-012fa0fb02c4"
    },
    {
      "fmParamsList": {
        "operator1": {
          "attack": 133.7713726952359,
          "decay": 458.5396534612792,
          "sustain": 361.2728241677204,
          "sustainTime": 384.7930358127095,
          "release": 419.9068535080879,
          "frequency": 78.67342838881967
        }
      },
      "fitness": 2.388508880744784,
      "pre_evaluation": 1.8563713120618857,
      "generation": 9,
      "chromosomeId": "efc2c10e-cbaf-4518-9318-302a1165980e"
    },
    {
      "fmParamsList": {
        "operator1": {
          "attack": 207.31865199279568,
          "decay": 367.4120722588555,
          "sustain": 271.935735892296,
          "sustainTime": 320.54134984002064,
          "release": 337.47726752591893,
          "frequency": 287.0297599025904
        }
      },
      "fitness": 2.388508880744784,
      "pre_evaluation": 1.8563729385444336,
      "generation": 9,
      "chromosomeId": "f704721e-4595-4247-8966-13680cd99401"
    },
    {
      "fmParamsList": {
        "operator1": {
          "attack": 232.1452437400527,
          "decay": 136.67263347662006,
          "sustain": 117.42789838073412,
          "sustainTime": 264.95172606860643,
          "release": 321.36459223523804,
          "frequency": 196.34271252435917
        }
      },
      "fitness": 2.388508880744784,
      "pre_evaluation": 1.8563768569574628,
      "generation": 9,
      "chromosomeId": "b2906ea9-f563-4ab4-8aa8-0f02678e8833"
    },
    {
      "fmParamsList": {
        "operator1": {
          "attack": 491.3100675267293,
          "decay": 172.05363286697713,
          "sustain": 318.1204382114803,
          "sustainTime": 355.18024709799283,
          "release": 121.19110467713081,
          "frequency": 395.78467031228854
        }
      },
      "fitness": 2.388508880744784,
      "pre_evaluation": 1.8563713120618857,
      "generation": 9,
      "chromosomeId": "6bcd578e-5536-4d12-9a99-c67613e62947"
    },
    {
      "fmParamsList": {
        "operator1": {
          "attack": 345.7834972557812,
          "decay": 269.76010562802907,
          "sustain": 324.78277596520684,
          "sustainTime": 189.50446027816275,
          "release": 441.2249263797916,
          "frequency": 270.4913589606872
        }
      },
      "fitness": 2.388508880744784,
      "pre_evaluation": 1.8563713120618857,
      "generation": 9,
      "chromosomeId": "98e12e2d-e614-4970-96d7-61022c13d162"
    },
    {
      "fmParamsList": {
        "operator1": {
          "attack": 90.65438171158046,
          "decay": 295.3305962360605,
          "sustain": 299.4377484233417,
          "sustainTime": 360.9281967947094,
          "release": 314.470778887338,
          "frequency": 308.3990514351759
        }
      },
      "fitness": 2.388508880744784,
      "pre_evaluation": 1.8563713120618857,
      "generation": 9,
      "chromosomeId": "7ecf8057-9ff3-4950-81d5-d2f6b16a942a"
    },
    {
      "fmParamsList": {
        "operator1": {
          "attack": 117.10598189178378,
          "decay": 181.21699779026986,
          "sustain": 256.2963474205111,
          "sustainTime": 253.08853671674245,
          "release": 304.5368393727519,
          "frequency": 206.1723025945691
        }
      },
      "fitness": 2.388508880744784,
      "pre_evaluation": 1.8643411600090067,
      "generation": 9,
      "chromosomeId": "cff622d4-d859-4700-8a0d-26044ed38517"
    },
    {
      "fmParamsList": {
        "operator1": {
          "attack": 276.09194864170644,
          "decay": 488.30072534707506,
          "sustain": 236.90535776277608,
          "sustainTime": 226.62274263812122,
          "release": 500,
          "frequency": 144.92120777000682
        }
      },
      "fitness": 2.388508880744784,
      "pre_evaluation": 1.856371312061886,
      "generation": 9,
      "chromosomeId": "181dba9c-e9d0-40db-a57c-da40e30166c7"
    },
    {
      "fmParamsList": {
        "operator1": {
          "attack": 291.68933111253875,
          "decay": 237.24226623852076,
          "sustain": 291.72208365535147,
          "sustainTime": 285.5534667998959,
          "release": 297.4484633705344,
          "frequency": 238.0979426653752
        }
      },
      "fitness": 4.766485489602785,
      "pre_evaluation": 2.0023756201905014,
      "generation": 9,
      "chromosomeId": "e353c37d-00c4-4385-99f9-9df3a0285e23"
    },
    {
      "fmParamsList": {
        "operator1": {
          "attack": 112.32882810660814,
          "decay": 240.70203353554243,
          "sustain": 266.724631964745,
          "sustainTime": 292.3160776629273,
          "release": 207.67558934863217,
          "frequency": 278.58722485551294
        }
      },
      "fitness": 2.3898047923856502,
      "pre_evaluation": 1.8646891289668641,
      "generation": 9,
      "chromosomeId": "b4000c40-0406-4a5b-8684-b6757afac8d6"
    },
    {
      "fmParamsList": {
        "operator1": {
          "attack": 35.827151836059215,
          "decay": 292.60060664782003,
          "sustain": 354.95325897111843,
          "sustainTime": 244.74094340551494,
          "release": 316.8408403266652,
          "frequency": 164.17805120988595
        }
      },
      "fitness": 2.388508880744784,
      "pre_evaluation": 1.8564548565156405,
      "generation": 9,
      "chromosomeId": "27feffc7-e9d8-495f-83bc-ae9644cdc019"
    },
    {
      "fmParamsList": {
        "operator1": {
          "attack": 133.76995772821553,
          "decay": 321.5963646212121,
          "sustain": 316.31514576716586,
          "sustainTime": 276.2090413739038,
          "release": 353.38862870875016,
          "frequency": 220.91813394310572
        }
      },
      "fitness": 2.388508880744784,
      "pre_evaluation": 2.3670144374736157,
      "generation": 9,
      "chromosomeId": "4b7eaf49-3af9-4912-9bcd-9ada7bcea866"
    },
    {
      "fmParamsList": {
        "operator1": {
          "attack": 315.4092043249898,
          "decay": 261.02907786120477,
          "sustain": 476.1520306227095,
          "sustainTime": 252.87374009563862,
          "release": 375.2497939089002,
          "frequency": 291.593937100061
        }
      },
      "fitness": 2.388508880744784,
      "pre_evaluation": 1.8563732512289008,
      "generation": 9,
      "chromosomeId": "82a35cd5-5108-4a2f-8279-ba0178f82d54"
    },
    {
      "fmParamsList": {
        "operator1": {
          "attack": 382.2417486769556,
          "decay": 238.2262528691653,
          "sustain": 480.0540908028697,
          "sustainTime": 340.15131314291824,
          "release": 263.85617921158166,
          "frequency": 396.25030060535624
        }
      },
      "fitness": 2.3885088807447854,
      "pre_evaluation": 1.8563713120618857,
      "generation": 9,
      "chromosomeId": "b229442f-f4b7-4229-b0ee-6bb5958a7e31"
    },
    {
      "fmParamsList": {
        "operator1": {
          "attack": 245.14939411026572,
          "decay": 266.8839863192288,
          "sustain": 287.6181866047783,
          "sustainTime": 411.90790396403196,
          "release": 500,
          "frequency": 376.2428474412929
        }
      },
      "fitness": 2.388508880744784,
      "pre_evaluation": 1.8563713120618857,
      "generation": 9,
      "chromosomeId": "fa88596e-2306-400a-9c27-18fe1fe172a9"
    },
    {
      "fmParamsList": {
        "operator1": {
          "attack": 328.70991339738146,
          "decay": 304.2760228145368,
          "sustain": 14.66501941674315,
          "sustainTime": 319.1275066392806,
          "release": 292.58576475331,
          "frequency": 155.83917888063058
        }
      },
      "fitness": 2.388508880744784,
      "pre_evaluation": 1.8563713120618857,
      "generation": 9,
      "chromosomeId": "bd95396a-d8a9-4c4c-848a-6fcd870cf360"
    },
    {
      "fmParamsList": {
        "operator1": {
          "attack": 472.5155569999583,
          "decay": 188.84901680245864,
          "sustain": 272.35297838354313,
          "sustainTime": 74.48045850086193,
          "release": 428.36718202416176,
          "frequency": 235.32517391691488
        }
      },
      "fitness": 2.388508880744784,
      "pre_evaluation": 1.8563713120618857,
      "generation": 9,
      "chromosomeId": "4b997bd7-51a8-40cb-ba08-597496f50b1e"
    },
    {
      "fmParamsList": {
        "operator1": {
          "attack": 0,
          "decay": 79.0698886499722,
          "sustain": 500,
          "sustainTime": 175.57470995940707,
          "release": 426.6117386805261,
          "frequency": 181.21294307190982
        }
      },
      "fitness": 2.388508880744784,
      "pre_evaluation": 1.8563713120618857,
      "generation": 9,
      "chromosomeId": "6f25e46c-ba3d-4c67-bcbb-7bb93e04a832"
    },
    {
      "fmParamsList": {
        "operator1": {
          "attack": 0,
          "decay": 241.44111974921873,
          "sustain": 386.1780707581543,
          "sustainTime": 171.11003936862681,
          "release": 308.819579397227,
          "frequency": 300.4597996691629
        }
      },
      "fitness": 2.38850888074934,
      "pre_evaluation": 1.8563713120618857,
      "generation": 9,
      "chromosomeId": "f383b3db-4497-4818-8d56-a87d6f252476"
    },
    {
      "fmParamsList": {
        "operator1": {
          "attack": 328.4663471117302,
          "decay": 343.6073292080014,
          "sustain": 270.7308464185438,
          "sustainTime": 266.1969029554109,
          "release": 220.38427024017986,
          "frequency": 377.64202899792855
        }
      },
      "fitness": 2.388508880744784,
      "pre_evaluation": 1.8566432026630229,
      "generation": 9,
      "chromosomeId": "9fc30efe-3668-40d4-9f0f-3287b787774c"
    },
    {
      "fmParamsList": {
        "operator1": {
          "attack": 340.01640841840344,
          "decay": 241.52997921092225,
          "sustain": 290.1482386539614,
          "sustainTime": 305.91841348350465,
          "release": 168.2453483397805,
          "frequency": 228.56008211087936
        }
      },
      "fitness": 2.452415716926451,
      "pre_evaluation": 1.8563720298124224,
      "generation": 9,
      "chromosomeId": "cff51a2b-af6f-4ebe-a6f7-750422076c71"
    },
    {
      "fmParamsList": {
        "operator1": {
          "attack": 314.48337926161446,
          "decay": 318.32182004219806,
          "sustain": 372.5343690875195,
          "sustainTime": 410.65618345222293,
          "release": 179.56003787409202,
          "frequency": 167.79459047054075
        }
      },
      "fitness": 2.388508880744784,
      "pre_evaluation": 1.8563713120618857,
      "generation": 9,
      "chromosomeId": "ac57d956-7fe9-4355-9606-51f81fdeb26c"
    },
    {
      "fmParamsList": {
        "operator1": {
          "attack": 353.5173778578169,
          "decay": 248.83252629973362,
          "sustain": 339.24880422685624,
          "sustainTime": 202.52127123932908,
          "release": 345.1998270447599,
          "frequency": 167.97213369845227
        }
      },
      "fitness": 2.388508880828955,
      "pre_evaluation": 1.8563713120618857,
      "generation": 9,
      "chromosomeId": "0c4bb6a7-54d6-4e84-a184-ba80a985b588"
    },
    {
      "fmParamsList": {
        "operator1": {
          "attack": 494.6193785249196,
          "decay": 430.91210072801425,
          "sustain": 277.17363053875334,
          "sustainTime": 212.09484580591527,
          "release": 251.03593158053482,
          "frequency": 281.093136821327
        }
      },
      "fitness": 2.388508880744784,
      "pre_evaluation": 1.8563713120618857,
      "generation": 9,
      "chromosomeId": "a72eeb01-58e2-4675-8726-7b356ba63fbc"
    },
    {
      "fmParamsList": {
        "operator1": {
          "attack": 380.2439255139633,
          "decay": 279.14539706967105,
          "sustain": 275.33350639023604,
          "sustainTime": 185.35868932568346,
          "release": 464.64600309748914,
          "frequency": 309.9591721592323
        }
      },
      "fitness": 2.388508880744784,
      "pre_evaluation": 1.8563713120618857,
      "generation": 9,
      "chromosomeId": "9dcefe5f-d920-4495-82e3-1c734d76b768"
    },
    {
      "fmParamsList": {
        "operator1": {
          "attack": 351.94058851878185,
          "decay": 246.1473458293117,
          "sustain": 441.12366404901996,
          "sustainTime": 215.76776121480998,
          "release": 487.7996753511822,
          "frequency": 286.58220133843474
        }
      },
      "fitness": 2.388508919580259,
      "pre_evaluation": 1.8563713120618857,
      "generation": 9,
      "chromosomeId": "dedded38-20e9-44b1-aa9b-6101e5058aaf"
    },
    {
      "fmParamsList": {
        "operator1": {
          "attack": 236.00661756786673,
          "decay": 216.7414139571353,
          "sustain": 316.2905111174125,
          "sustainTime": 325.45670780506714,
          "release": 205.7125529747537,
          "frequency": 500
        }
      },
      "fitness": 2.388508880744784,
      "pre_evaluation": 1.8563713120634326,
      "generation": 9,
      "chromosomeId": "82ffa7ca-0cfc-45b8-9d79-b78e56e7f878"
    },
    {
      "fmParamsList": {
        "operator1": {
          "attack": 239.181154734489,
          "decay": 256.20869278784437,
          "sustain": 326.4041533555248,
          "sustainTime": 237.44494841960892,
          "release": 291.42075736875245,
          "frequency": 252.80844842605705
        }
      },
      "fitness": 2.388508880744786,
      "pre_evaluation": 1.8564915420927903,
      "generation": 9,
      "chromosomeId": "4d96d192-5248-43ed-996d-06c330f09075"
    },
    {
      "fmParamsList": {
        "operator1": {
          "attack": 169.65326044059154,
          "decay": 221.47557989027882,
          "sustain": 500,
          "sustainTime": 96.0795254890113,
          "release": 71.23724820590267,
          "frequency": 0
        }
      },
      "fitness": 2.388508880744784,
      "pre_evaluation": 1.8563713120618857,
      "generation": 9,
      "chromosomeId": "c2871770-58ee-4529-a0f7-e47d6739a049"
    },
    {
      "fmParamsList": {
        "operator1": {
          "attack": 357.9280330374567,
          "decay": 258.45274170666437,
          "sustain": 398.96131466251364,
          "sustainTime": 432.03023417802854,
          "release": 417.7395063424224,
          "frequency": 288.2992951884622
        }
      },
      "fitness": 2.388508880744784,
      "pre_evaluation": 1.8563713120618857,
      "generation": 9,
      "chromosomeId": "b31a7924-57b7-4b4c-974f-b1b716f7f1e9"
    },
    {
      "fmParamsList": {
        "operator1": {
          "attack": 73.61207073370204,
          "decay": 175.30972315305516,
          "sustain": 268.98613114564205,
          "sustainTime": 288.2761773817928,
          "release": 33.97734099697003,
          "frequency": 488.13732729183045
        }
      },
      "fitness": 2.388508880744784,
      "pre_evaluation": 1.856371312061888,
      "generation": 9,
      "chromosomeId": "b3459783-6bd0-4740-9cd5-1e8e75a4ed23"
    },
    {
      "fmParamsList": {
        "operator1": {
          "attack": 349.27815702000316,
          "decay": 241.40404544010406,
          "sustain": 249.48395575791025,
          "sustainTime": 356.30842890475594,
          "release": 268.2844229123723,
          "frequency": 334.72854347535844
        }
      },
      "fitness": 2.3885089624849813,
      "pre_evaluation": 1.8563713120618857,
      "generation": 9,
      "chromosomeId": "b074e9b3-10c4-4a97-8969-cd6932330ad0"
    },
    {
      "fmParamsList": {
        "operator1": {
          "attack": 336.03235163362064,
          "decay": 234.5105962143709,
          "sustain": 285.9254650350346,
          "sustainTime": 435.20147917979654,
          "release": 500,
          "frequency": 304.7737846259105
        }
      },
      "fitness": 2.3885088807500074,
      "pre_evaluation": 1.8563713120618857,
      "generation": 9,
      "chromosomeId": "fd0cb944-debf-4c19-b8ec-84b810a5e848"
    },
    {
      "fmParamsList": {
        "operator1": {
          "attack": 142.27801489440577,
          "decay": 280.410360407202,
          "sustain": 295.8657289448088,
          "sustainTime": 242.4981479303615,
          "release": 362.3269299464528,
          "frequency": 173.02101988012208
        }
      },
      "fitness": 2.388508880744784,
      "pre_evaluation": 1.8565463730525529,
      "generation": 9,
      "chromosomeId": "fedb84c4-4b7d-49fa-9420-5c833580995e"
    },
    {
      "fmParamsList": {
        "operator1": {
          "attack": 273.963352388516,
          "decay": 326.12660654620333,
          "sustain": 277.8578417292141,
          "sustainTime": 437.4611557731472,
          "release": 178.5680352693057,
          "frequency": 366.5034021242237
        }
      },
      "fitness": 2.388508880744784,
      "pre_evaluation": 1.8563713120618857,
      "generation": 9,
      "chromosomeId": "6a318a2a-7406-4750-be63-06c2e72282f3"
    },
    {
      "fmParamsList": {
        "operator1": {
          "attack": 500,
          "decay": 310.8416021693923,
          "sustain": 372.6971991165593,
          "sustainTime": 222.12719769189607,
          "release": 281.44724250520983,
          "frequency": 157.66910094119967
        }
      },
      "fitness": 2.388508880744784,
      "pre_evaluation": 1.8563713120618888,
      "generation": 9,
      "chromosomeId": "ebb78e20-09c8-4af7-9f7e-e5c9a7c391d3"
    },
    {
      "fmParamsList": {
        "operator1": {
          "attack": 97.49862363173287,
          "decay": 271.0747874771597,
          "sustain": 332.8035396884112,
          "sustainTime": 285.6397979752092,
          "release": 445.2595236884338,
          "frequency": 68.32205365224488
        }
      },
      "fitness": 2.388508880744784,
      "pre_evaluation": 1.8563745269766425,
      "generation": 9,
      "chromosomeId": "dddb5c15-ca98-48d5-bc22-1487350e826b"
    },
    {
      "fmParamsList": {
        "operator1": {
          "attack": 59.63449154734312,
          "decay": 471.9425382171606,
          "sustain": 358.9510258787023,
          "sustainTime": 194.68394389154216,
          "release": 267.763179829599,
          "frequency": 266.3763807694995
        }
      },
      "fitness": 2.388508880744784,
      "pre_evaluation": 1.8563713120618857,
      "generation": 9,
      "chromosomeId": "a49dfa81-8dad-468f-a2d0-058dd41b914f"
    },
    {
      "fmParamsList": {
        "operator1": {
          "attack": 453.5038941764427,
          "decay": 244.76641258838788,
          "sustain": 321.17492523464034,
          "sustainTime": 425.99629395396073,
          "release": 451.0169491953537,
          "frequency": 267.1037708492255
        }
      },
      "fitness": 2.38850888075259,
      "pre_evaluation": 1.8563713120618857,
      "generation": 9,
      "chromosomeId": "9830734c-a82f-4bab-90b8-69cefd32be1b"
    },
    {
      "fmParamsList": {
        "operator1": {
          "attack": 346.84113940421696,
          "decay": 169.09288392506426,
          "sustain": 333.1200262064629,
          "sustainTime": 265.2637332942245,
          "release": 421.5507941247911,
          "frequency": 164.43699898332906
        }
      },
      "fitness": 2.388508880744784,
      "pre_evaluation": 1.8563912940804947,
      "generation": 9,
      "chromosomeId": "aaff1e72-e95d-4f7a-b0f1-79a2426692ec"
    },
    {
      "fmParamsList": {
        "operator1": {
          "attack": 107.39021812184993,
          "decay": 163.27112062725683,
          "sustain": 265.89160462865266,
          "sustainTime": 282.67506025359506,
          "release": 393.9354999672864,
          "frequency": 213.24740705900075
        }
      },
      "fitness": 2.388508880744784,
      "pre_evaluation": 1.864649434881442,
      "generation": 9,
      "chromosomeId": "29c6c55b-2a45-4bd8-8180-876637e8e403"
    },
    {
      "fmParamsList": {
        "operator1": {
          "attack": 83.78462120842947,
          "decay": 251.5564341158602,
          "sustain": 326.56820570164723,
          "sustainTime": 275.5566536205633,
          "release": 145.19093514395595,
          "frequency": 391.13087100030725
        }
      },
      "fitness": 2.388508880744784,
      "pre_evaluation": 1.856392174374957,
      "generation": 9,
      "chromosomeId": "07826405-3874-4ae1-836c-0cfd121262f7"
    },
    {
      "fmParamsList": {
        "operator1": {
          "attack": 500,
          "decay": 197.85127287576853,
          "sustain": 266.6668528641467,
          "sustainTime": 264.1912343899204,
          "release": 85.05609720420239,
          "frequency": 258.7151363641708
        }
      },
      "fitness": 2.388508880744784,
      "pre_evaluation": 1.8563713120620082,
      "generation": 9,
      "chromosomeId": "78cd3173-2292-4d09-86ee-9e301da8788f"
    },
    {
      "fmParamsList": {
        "operator1": {
          "attack": 100.7038468431692,
          "decay": 372.1114118282011,
          "sustain": 187.7493885255856,
          "sustainTime": 410.7964711211663,
          "release": 293.7650905821153,
          "frequency": 288.1884801372089
        }
      },
      "fitness": 2.388508880744784,
      "pre_evaluation": 1.8563713120618857,
      "generation": 9,
      "chromosomeId": "1006e845-41b5-4e9b-8428-a0c2c6f862f4"
    },
    {
      "fmParamsList": {
        "operator1": {
          "attack": 346.0769938208134,
          "decay": 279.3630546181429,
          "sustain": 289.201770168649,
          "sustainTime": 338.7898937978633,
          "release": 357.05869483475203,
          "frequency": 298.4588529926929
        }
      },
      "fitness": 2.388508880744784,
      "pre_evaluation": 1.8563713120621623,
      "generation": 9,
      "chromosomeId": "1bcf45d7-959b-4042-b728-4a559c8a783a"
    },
    {
      "fmParamsList": {
        "operator1": {
          "attack": 428.30728046866415,
          "decay": 262.34513744248915,
          "sustain": 268.26126221791867,
          "sustainTime": 274.4134171030499,
          "release": 251.93719109795808,
          "frequency": 465.9559189983794
        }
      },
      "fitness": 2.388508880744784,
      "pre_evaluation": 1.8563714181460726,
      "generation": 9,
      "chromosomeId": "ad4e4a71-94ac-44d8-bb56-7e8b0f8bc67f"
    },
    {
      "fmParamsList": {
        "operator1": {
          "attack": 40.36421961148425,
          "decay": 88.82440841085744,
          "sustain": 282.42742283101256,
          "sustainTime": 255.7975147741637,
          "release": 465.01456594134015,
          "frequency": 215.8596303798206
        }
      },
      "fitness": 2.388508880744784,
      "pre_evaluation": 1.8563714171850108,
      "generation": 9,
      "chromosomeId": "97299348-9528-40e0-9b2d-5237cf90ed5e"
    },
    {
      "fmParamsList": {
        "operator1": {
          "attack": 233.13679847140133,
          "decay": 244.02581255166754,
          "sustain": 336.97128934923495,
          "sustainTime": 223.98344630396284,
          "release": 235.44197698272313,
          "frequency": 328.95291728844893
        }
      },
      "fitness": 2.388508926576859,
      "pre_evaluation": 1.856371319548938,
      "generation": 9,
      "chromosomeId": "de0e706f-5717-4eb1-86ba-26932bd6548e"
    },
    {
      "fmParamsList": {
        "operator1": {
          "attack": 161.45417698016487,
          "decay": 215.8471329924032,
          "sustain": 317.92166567416336,
          "sustainTime": 268.01277136830447,
          "release": 412.20211986450954,
          "frequency": 339.93175665029304
        }
      },
      "fitness": 2.388508880744784,
      "pre_evaluation": 1.8622488612510928,
      "generation": 9,
      "chromosomeId": "78b5debe-6f3d-4b80-9885-81c366838b66"
    },
    {
      "fmParamsList": {
        "operator1": {
          "attack": 24.954525145070633,
          "decay": 344.78907203268386,
          "sustain": 287.03767550986356,
          "sustainTime": 307.39544293567656,
          "release": 309.28976148863643,
          "frequency": 179.0471092296953
        }
      },
      "fitness": 2.388508880744784,
      "pre_evaluation": 1.8564385375982428,
      "generation": 9,
      "chromosomeId": "6404cfc3-4a7e-41ec-aed4-406071c9a1fc"
    },
    {
      "fmParamsList": {
        "operator1": {
          "attack": 392.71070474606074,
          "decay": 210.5636573552701,
          "sustain": 500,
          "sustainTime": 352.5528083629261,
          "release": 0,
          "frequency": 264.7905429637019
        }
      },
      "fitness": 2.388508880744784,
      "pre_evaluation": 1.8563713120618857,
      "generation": 9,
      "chromosomeId": "f85e78d2-4178-4797-8fc2-d290ac263ead"
    },
    {
      "fmParamsList": {
        "operator1": {
          "attack": 385.9411382652762,
          "decay": 172.2105218445049,
          "sustain": 368.2371452039397,
          "sustainTime": 232.04650431201375,
          "release": 478.4684973234684,
          "frequency": 129.4431962420354
        }
      },
      "fitness": 2.388508880744784,
      "pre_evaluation": 1.8563713120619167,
      "generation": 9,
      "chromosomeId": "ad16c65a-482a-4e33-bf90-25812191dbfb"
    },
    {
      "fmParamsList": {
        "operator1": {
          "attack": 491.5050250310504,
          "decay": 318.6183874452201,
          "sustain": 173.10902560014353,
          "sustainTime": 77.27582457118218,
          "release": 232.2711580733644,
          "frequency": 275.2051621824893
        }
      },
      "fitness": 2.388508880744784,
      "pre_evaluation": 1.8563713120618857,
      "generation": 9,
      "chromosomeId": "89b294ac-8a28-4911-9acb-a296703e255d"
    },
    {
      "fmParamsList": {
        "operator1": {
          "attack": 342.2999797211827,
          "decay": 177.40257296034227,
          "sustain": 492.18670201953273,
          "sustainTime": 239.93894650311597,
          "release": 164.54639133487396,
          "frequency": 229.90011136809017
        }
      },
      "fitness": 2.388508880744784,
      "pre_evaluation": 1.8563713120799057,
      "generation": 9,
      "chromosomeId": "313f475c-04a7-4da1-9d7e-f47369c8888b"
    },
    {
      "fmParamsList": {
        "operator1": {
          "attack": 0,
          "decay": 280.1861153965364,
          "sustain": 307.30373061485784,
          "sustainTime": 419.34589930689583,
          "release": 475.3161225547535,
          "frequency": 212.47568678266782
        }
      },
      "fitness": 2.388508880744784,
      "pre_evaluation": 1.8563713120618857,
      "generation": 9,
      "chromosomeId": "47b99d26-0539-4d0c-85b2-563b2891b2fe"
    },
    {
      "fmParamsList": {
        "operator1": {
          "attack": 198.95669114175521,
          "decay": 248.48401013507498,
          "sustain": 0.6408722000244325,
          "sustainTime": 217.4204559654326,
          "release": 239.62058087577824,
          "frequency": 246.30073250465864
        }
      },
      "fitness": 2.388508884605205,
      "pre_evaluation": 1.8563713120618857,
      "generation": 9,
      "chromosomeId": "7da60934-5ca7-4d4f-940e-c7151de8936a"
    },
    {
      "fmParamsList": {
        "operator1": {
          "attack": 440.22154462820845,
          "decay": 82.14402533036858,
          "sustain": 255.9363542495376,
          "sustainTime": 313.0439884316197,
          "release": 90.93584428751745,
          "frequency": 276.31600445839985
        }
      },
      "fitness": 2.388508880744784,
      "pre_evaluation": 1.8563713120618865,
      "generation": 9,
      "chromosomeId": "e7f1fc96-e962-4969-9b06-fd657d1a657b"
    },
    {
      "fmParamsList": {
        "operator1": {
          "attack": 288.0352826799883,
          "decay": 291.36759673062454,
          "sustain": 308.7250019628894,
          "sustainTime": 220.78677446851685,
          "release": 0,
          "frequency": 334.77276742500135
        }
      },
      "fitness": 2.388508880744784,
      "pre_evaluation": 1.8563713120618857,
      "generation": 9,
      "chromosomeId": "41e3ec0f-692c-4c5a-a69f-8b19a781692b"
    },
    {
      "fmParamsList": {
        "operator1": {
          "attack": 308.970382846597,
          "decay": 298.2017948712859,
          "sustain": 269.9338352140365,
          "sustainTime": 274.6215580282359,
          "release": 482.99270168137355,
          "frequency": 259.6398968027946
        }
      },
      "fitness": 2.388508880744784,
      "pre_evaluation": 1.8563736556927313,
      "generation": 9,
      "chromosomeId": "37ee1053-c2cc-43ea-a975-1891a7457845"
    },
    {
      "fmParamsList": {
        "operator1": {
          "attack": 341.3327361949072,
          "decay": 276.91478985485907,
          "sustain": 323.2655875387862,
          "sustainTime": 255.72301328396426,
          "release": 156.1469641882274,
          "frequency": 195.00190295586063
        }
      },
      "fitness": 2.388508880744784,
      "pre_evaluation": 1.8563751200453171,
      "generation": 9,
      "chromosomeId": "2dd34fcc-6308-4e1a-8d25-303e0fd61670"
    },
    {
      "fmParamsList": {
        "operator1": {
          "attack": 500,
          "decay": 322.07268094403804,
          "sustain": 356.14902774988957,
          "sustainTime": 348.1095382963463,
          "release": 190.29189868751146,
          "frequency": 267.72776682266897
        }
      },
      "fitness": 2.388508880744784,
      "pre_evaluation": 1.8563713120618857,
      "generation": 9,
      "chromosomeId": "f1be5885-6936-4b8e-a773-dc110fadbd4e"
    },
    {
      "fmParamsList": {
        "operator1": {
          "attack": 110.35225076730569,
          "decay": 347.1847537387282,
          "sustain": 183.86920129521567,
          "sustainTime": 287.7458801398199,
          "release": 212.8772843715572,
          "frequency": 262.99438349804956
        }
      },
      "fitness": 2.388508880744784,
      "pre_evaluation": 1.85688455763326,
      "generation": 9,
      "chromosomeId": "770118b0-85cf-435f-a0b8-9bfe15449211"
    },
    {
      "fmParamsList": {
        "operator1": {
          "attack": 325.4793530950718,
          "decay": 132.27568373381206,
          "sustain": 212.92748134924278,
          "sustainTime": 188.40487022491627,
          "release": 170.45358335490835,
          "frequency": 343.79081236843695
        }
      },
      "fitness": 2.388508880744784,
      "pre_evaluation": 1.8563713120618857,
      "generation": 9,
      "chromosomeId": "a132239f-a203-4749-afad-4166bd11f61d"
    },
    {
      "fmParamsList": {
        "operator1": {
          "attack": 326.31196044486836,
          "decay": 323.41710509481294,
          "sustain": 202.11594844742575,
          "sustainTime": 207.92022532791825,
          "release": 140.6596115508891,
          "frequency": 227.44713820758423
        }
      },
      "fitness": 2.388508880744784,
      "pre_evaluation": 1.8563713120618857,
      "generation": 9,
      "chromosomeId": "1c53f92d-b18d-4753-9777-95a4f9ce3d32"
    },
    {
      "fmParamsList": {
        "operator1": {
          "attack": 299.25502118690724,
          "decay": 111.32079729330418,
          "sustain": 370.1277556296415,
          "sustainTime": 285.99384357665434,
          "release": 305.0207719766497,
          "frequency": 300.9505202217145
        }
      },
      "fitness": 2.388508880744784,
      "pre_evaluation": 1.8628223386196274,
      "generation": 9,
      "chromosomeId": "3c4e8db7-d960-428e-b884-076e893b74b6"
    },
    {
      "fmParamsList": {
        "operator1": {
          "attack": 61.48774808796988,
          "decay": 49.81966699616123,
          "sustain": 327.8797981435973,
          "sustainTime": 403.88349528158363,
          "release": 377.2325846928549,
          "frequency": 375.06824245257224
        }
      },
      "fitness": 2.388508880744784,
      "pre_evaluation": 1.8563713120618857,
      "generation": 9,
      "chromosomeId": "1b454168-c25a-499e-9096-b967d1020cc5"
    },
    {
      "fmParamsList": {
        "operator1": {
          "attack": 59.34013886144194,
          "decay": 387.2395427344471,
          "sustain": 318.9483834015437,
          "sustainTime": 346.09688478749786,
          "release": 132.26218353613723,
          "frequency": 165.2614112483155
        }
      },
      "fitness": 2.388508880744784,
      "pre_evaluation": 1.8563713120618857,
      "generation": 9,
      "chromosomeId": "e85da35c-e6c1-49a1-bb07-076fa49326da"
    },
    {
      "fmParamsList": {
        "operator1": {
          "attack": 44.04946888748351,
          "decay": 209.52954870981517,
          "sustain": 238.64618629496198,
          "sustainTime": 289.7718951869571,
          "release": 375.66501350412125,
          "frequency": 283.3264305906576
        }
      },
      "fitness": 2.388508880744784,
      "pre_evaluation": 1.8580529688037666,
      "generation": 9,
      "chromosomeId": "3e27dc00-8e9b-48be-9eac-04a2bb688f9e"
    },
    {
      "fmParamsList": {
        "operator1": {
          "attack": 148.2477392800212,
          "decay": 500,
          "sustain": 0,
          "sustainTime": 269.65309781778626,
          "release": 239.69218725885463,
          "frequency": 217.4873690987913
        }
      },
      "fitness": 2.388508880744784,
      "pre_evaluation": 1.856371312062253,
      "generation": 9,
      "chromosomeId": "7ae4f4ab-0de1-4256-ad88-466cc127dfb9"
    },
    {
      "fmParamsList": {
        "operator1": {
          "attack": 42.911019851139244,
          "decay": 205.48667604209155,
          "sustain": 500,
          "sustainTime": 245.60543600602324,
          "release": 206.94760049308996,
          "frequency": 0
        }
      },
      "fitness": 2.388508880744784,
      "pre_evaluation": 1.8563713120626084,
      "generation": 9,
      "chromosomeId": "cc33b21d-d30d-400f-baa0-f7ceb95b8803"
    },
    {
      "fmParamsList": {
        "operator1": {
          "attack": 52.11412839193906,
          "decay": 348.3890360929792,
          "sustain": 360.4877533185737,
          "sustainTime": 291.20292326605113,
          "release": 481.96096553743376,
          "frequency": 181.4887815269768
        }
      },
      "fitness": 2.388508880744784,
      "pre_evaluation": 1.856371691526689,
      "generation": 9,
      "chromosomeId": "b4c8b388-2a04-43c1-a149-ce05729a73ce"
    },
    {
      "fmParamsList": {
        "operator1": {
          "attack": 226.57939181630775,
          "decay": 276.9831205845563,
          "sustain": 446.807060358386,
          "sustainTime": 302.1112635349419,
          "release": 78.16657713092127,
          "frequency": 298.2789664888654
        }
      },
      "fitness": 2.388508880744784,
      "pre_evaluation": 1.8563713121261898,
      "generation": 9,
      "chromosomeId": "d24a07fe-4db1-464f-8430-aea7dd67e2f2"
    },
    {
      "fmParamsList": {
        "operator1": {
          "attack": 166.31263722422895,
          "decay": 259.75744288022815,
          "sustain": 334.3642747539036,
          "sustainTime": 322.37549569613884,
          "release": 78.67104695578365,
          "frequency": 242.70194850625626
        }
      },
      "fitness": 2.388508880744784,
      "pre_evaluation": 1.8563713120626277,
      "generation": 9,
      "chromosomeId": "f06434d6-c17d-414c-ad34-0dc197ddf216"
    },
    {
      "fmParamsList": {
        "operator1": {
          "attack": 82.09332499375216,
          "decay": 233.43052491344974,
          "sustain": 282.25415962839514,
          "sustainTime": 306.8382995266377,
          "release": 386.4076215325794,
          "frequency": 230.97481174091834
        }
      },
      "fitness": 2.3898000268481163,
      "pre_evaluation": 1.8564867969280325,
      "generation": 9,
      "chromosomeId": "47094343-2080-4171-98f8-fd04846f7f0d"
    },
    {
      "fmParamsList": {
        "operator1": {
          "attack": 500,
          "decay": 262.5058901277998,
          "sustain": 294.3712199532406,
          "sustainTime": 233.3165361913659,
          "release": 323.8429152759262,
          "frequency": 228.19499047694325
        }
      },
      "fitness": 2.388508880744784,
      "pre_evaluation": 1.8563713120772445,
      "generation": 9,
      "chromosomeId": "120e3760-8a15-45db-a9b6-1eb87797fc4b"
    },
    {
      "fmParamsList": {
        "operator1": {
          "attack": 212.54148776105478,
          "decay": 244.75799111671162,
          "sustain": 374.5206532048921,
          "sustainTime": 154.32545997792408,
          "release": 341.5020699885887,
          "frequency": 267.2396166376723
        }
      },
      "fitness": 2.3885088830134125,
      "pre_evaluation": 1.8563713120618857,
      "generation": 9,
      "chromosomeId": "0bbef0fe-c40a-4c2c-a80e-90b7a18eb451"
    },
    {
      "fmParamsList": {
        "operator1": {
          "attack": 423.7560042232035,
          "decay": 256.6698009520803,
          "sustain": 307.2395628884354,
          "sustainTime": 340.9055926647004,
          "release": 368.42413322881964,
          "frequency": 53.82039265262068
        }
      },
      "fitness": 2.388508880744784,
      "pre_evaluation": 1.8563713120618857,
      "generation": 9,
      "chromosomeId": "5eb7588c-fb1d-48d9-879d-c00c8d6922b9"
    },
    {
      "fmParamsList": {
        "operator1": {
          "attack": 320.600350319125,
          "decay": 287.58918030252784,
          "sustain": 308.9360149222861,
          "sustainTime": 124.72141460604442,
          "release": 359.9826377619388,
          "frequency": 273.81573293542783
        }
      },
      "fitness": 2.388508880744784,
      "pre_evaluation": 1.8563713120618857,
      "generation": 9,
      "chromosomeId": "f2ec7fb2-f630-4191-8674-44801c2e0fe1"
    },
    {
      "fmParamsList": {
        "operator1": {
          "attack": 481.41328509008406,
          "decay": 238.4587473957844,
          "sustain": 90.75599709925422,
          "sustainTime": 288.07596355486436,
          "release": 318.52366520752656,
          "frequency": 102.71893504752771
        }
      },
      "fitness": 2.388508880746092,
      "pre_evaluation": 1.8563713120623193,
      "generation": 9,
      "chromosomeId": "97be845f-6d85-4b60-8469-94377850c30a"
    },
    {
      "fmParamsList": {
        "operator1": {
          "attack": 17.62103388103231,
          "decay": 299.65775677856993,
          "sustain": 270.87169929024867,
          "sustainTime": 353.25148342176635,
          "release": 284.0926970140821,
          "frequency": 190.28681830821574
        }
      },
      "fitness": 2.388508880744784,
      "pre_evaluation": 1.8563713120618857,
      "generation": 9,
      "chromosomeId": "50c6edc3-6bb7-4359-a8ef-f4192f2a7f8e"
    },
    {
      "fmParamsList": {
        "operator1": {
          "attack": 101.53073060131774,
          "decay": 208.51403400425477,
          "sustain": 257.2087113826296,
          "sustainTime": 259.97527053546446,
          "release": 320.8917137056464,
          "frequency": 234.20242095661666
        }
      },
      "fitness": 2.388508880744784,
      "pre_evaluation": 1.9105230516282752,
      "generation": 9,
      "chromosomeId": "ab36ae0d-4776-4ba2-869c-9ddc5f830271"
    },
    {
      "fmParamsList": {
        "operator1": {
          "attack": 188.9342130479496,
          "decay": 237.75017564583482,
          "sustain": 323.0426956611032,
          "sustainTime": 195.00404146182564,
          "release": 239.9719060798999,
          "frequency": 320.82431962299347
        }
      },
      "fitness": 2.388509105389295,
      "pre_evaluation": 1.8563713120618857,
      "generation": 9,
      "chromosomeId": "4a1683ad-0b31-4057-a7c6-6bf3e43b7f08"
    },
    {
      "fmParamsList": {
        "operator1": {
          "attack": 50.857170681354965,
          "decay": 217.72739832334594,
          "sustain": 317.9311474778692,
          "sustainTime": 282.56245270229357,
          "release": 200.99330543255226,
          "frequency": 115.07168458010595
        }
      },
      "fitness": 2.388508880744784,
      "pre_evaluation": 1.8568213675290213,
      "generation": 9,
      "chromosomeId": "83a007e4-b115-49cc-893d-c83aa7ff2c24"
    },
    {
      "fmParamsList": {
        "operator1": {
          "attack": 462.8417589092624,
          "decay": 90.03362918032394,
          "sustain": 305.1943472692688,
          "sustainTime": 293.50555127677995,
          "release": 166.14325991333578,
          "frequency": 338.08477107241606
        }
      },
      "fitness": 2.388508880744784,
      "pre_evaluation": 1.856371312490503,
      "generation": 9,
      "chromosomeId": "d705a110-d1ec-4e33-a4b8-79f59561a9d4"
    },
    {
      "fmParamsList": {
        "operator1": {
          "attack": 346.79416040461535,
          "decay": 240.8706648805121,
          "sustain": 227.7216333173666,
          "sustainTime": 255.7674831594883,
          "release": 500,
          "frequency": 500
        }
      },
      "fitness": 2.388508880744784,
      "pre_evaluation": 1.8563713120619847,
      "generation": 9,
      "chromosomeId": "516e881a-29e8-423f-802c-b30991a20da8"
    },
    {
      "fmParamsList": {
        "operator1": {
          "attack": 285.9947029478239,
          "decay": 230.57295449372617,
          "sustain": 289.38571709561626,
          "sustainTime": 313.0206923322391,
          "release": 307.97744150635344,
          "frequency": 297.7614745824062
        }
      },
      "fitness": 2.3888484573124154,
      "pre_evaluation": 1.856418106259817,
      "generation": 9,
      "chromosomeId": "9de32bf4-82ef-4b49-b2d1-3154606026d4"
    },
    {
      "fmParamsList": {
        "operator1": {
          "attack": 278.9907855999154,
          "decay": 230.66446821091222,
          "sustain": 336.42644176847637,
          "sustainTime": 271.7460699785554,
          "release": 333.3134435568826,
          "frequency": 385.877101252071
        }
      },
      "fitness": 2.3885088807449373,
      "pre_evaluation": 1.8725047702964535,
      "generation": 9,
      "chromosomeId": "01515e9a-f17f-42f3-bdbc-a42a5f7ba648"
    },
    {
      "fmParamsList": {
        "operator1": {
          "attack": 387.54851781038366,
          "decay": 297.302663702994,
          "sustain": 251.18173611127912,
          "sustainTime": 231.89251089778227,
          "release": 343.0121712298664,
          "frequency": 233.20579512439582
        }
      },
      "fitness": 2.388508880744784,
      "pre_evaluation": 1.8563713176374306,
      "generation": 9,
      "chromosomeId": "56fa13a4-e704-4651-9728-bf8440beb15e"
    },
    {
      "fmParamsList": {
        "operator1": {
          "attack": 242.81172626925806,
          "decay": 0,
          "sustain": 346.64215273936054,
          "sustainTime": 302.3080339721973,
          "release": 290.8703976213345,
          "frequency": 340.5237477839372
        }
      },
      "fitness": 2.388508880744784,
      "pre_evaluation": 1.8563816768551684,
      "generation": 9,
      "chromosomeId": "ab0229fe-b509-4b67-82b8-3e580c096c1e"
    },
    {
      "fmParamsList": {
        "operator1": {
          "attack": 246.89652218635382,
          "decay": 123.25200728492364,
          "sustain": 284.86722008188997,
          "sustainTime": 293.27671479636894,
          "release": 433.4442729574551,
          "frequency": 154.58895478095164
        }
      },
      "fitness": 2.388508880744784,
      "pre_evaluation": 1.8563867084180299,
      "generation": 9,
      "chromosomeId": "897ac7b3-056e-429e-8d95-0d4128c1a69b"
    },
    {
      "fmParamsList": {
        "operator1": {
          "attack": 319.86227200779194,
          "decay": 400.7440261471956,
          "sustain": 294.21510921970804,
          "sustainTime": 0,
          "release": 401.97144937010694,
          "frequency": 314.3026646010313
        }
      },
      "fitness": 2.388508880744784,
      "pre_evaluation": 1.8563713120618857,
      "generation": 9,
      "chromosomeId": "9ee5fe05-f479-4b79-8c93-7d1b5726c179"
    },
    {
      "fmParamsList": {
        "operator1": {
          "attack": 65.29893407381805,
          "decay": 349.3094435343531,
          "sustain": 327.1396238839501,
          "sustainTime": 273.5393687470103,
          "release": 268.15999185173257,
          "frequency": 320.2729158031261
        }
      },
      "fitness": 2.388508880744784,
      "pre_evaluation": 1.9661530168704038,
      "generation": 9,
      "chromosomeId": "51a9842a-6e1e-4771-a969-35d12508fdbb"
    },
    {
      "fmParamsList": {
        "operator1": {
          "attack": 240.68868290577183,
          "decay": 203.7758112839885,
          "sustain": 414.3074093201486,
          "sustainTime": 209.50644764098948,
          "release": 358.9421827886224,
          "frequency": 374.52912030582775
        }
      },
      "fitness": 2.388508880744784,
      "pre_evaluation": 1.8563713120618899,
      "generation": 9,
      "chromosomeId": "88765aae-a4c6-4a78-9d35-587f44f0ec52"
    },
    {
      "fmParamsList": {
        "operator1": {
          "attack": 143.80414132408228,
          "decay": 123.10771948102787,
          "sustain": 232.54421270957033,
          "sustainTime": 365.18881716762667,
          "release": 58.543903014315724,
          "frequency": 185.54659065020556
        }
      },
      "fitness": 2.388508880744784,
      "pre_evaluation": 1.8563713120618857,
      "generation": 9,
      "chromosomeId": "c7c93b5a-a90d-4351-9fa5-7cdb9fe3c439"
    },
    {
      "fmParamsList": {
        "operator1": {
          "attack": 38.04070331883649,
          "decay": 315.5560835864595,
          "sustain": 301.22290704583594,
          "sustainTime": 279.4246425681487,
          "release": 0,
          "frequency": 261.6723308637595
        }
      },
      "fitness": 2.388508880744784,
      "pre_evaluation": 1.856371312061958,
      "generation": 9,
      "chromosomeId": "55a79789-bb90-4d08-9c55-e7827f0a9eab"
    },
    {
      "fmParamsList": {
        "operator1": {
          "attack": 172.03588118787314,
          "decay": 67.81882603762045,
          "sustain": 410.98996441338346,
          "sustainTime": 146.56930039640346,
          "release": 0,
          "frequency": 273.38261601723934
        }
      },
      "fitness": 2.388508880744784,
      "pre_evaluation": 1.8563713120618857,
      "generation": 9,
      "chromosomeId": "f4296944-89cb-41b2-962e-48cb0655c503"
    },
    {
      "fmParamsList": {
        "operator1": {
          "attack": 110.38030217388338,
          "decay": 237.56363942248697,
          "sustain": 216.9585974638132,
          "sustainTime": 208.08315255466334,
          "release": 498.9414862718282,
          "frequency": 307.9412141001667
        }
      },
      "fitness": 2.3885089272200575,
      "pre_evaluation": 1.8563713120618857,
      "generation": 9,
      "chromosomeId": "2d5bbe67-a828-42b1-9d54-009ca3a1ebfd"
    },
    {
      "fmParamsList": {
        "operator1": {
          "attack": 19.543885234452574,
          "decay": 267.675595208678,
          "sustain": 439.6647744862887,
          "sustainTime": 310.6453443856525,
          "release": 462.06326449192204,
          "frequency": 67.97889210698756
        }
      },
      "fitness": 2.388508880744784,
      "pre_evaluation": 1.8563713120639769,
      "generation": 9,
      "chromosomeId": "9e4d3305-c61a-4863-b94d-59a20204aff1"
    },
    {
      "fmParamsList": {
        "operator1": {
          "attack": 0,
          "decay": 122.7258267935434,
          "sustain": 410.86187397188786,
          "sustainTime": 303.4650489497025,
          "release": 404.83465450301674,
          "frequency": 56.10632062364234
        }
      },
      "fitness": 2.388508880744784,
      "pre_evaluation": 1.8563713126785812,
      "generation": 9,
      "chromosomeId": "39155115-f070-41d6-ac3c-b7d29999d172"
    },
    {
      "fmParamsList": {
        "operator1": {
          "attack": 453.03538020962026,
          "decay": 208.24858978427432,
          "sustain": 255.91445587720182,
          "sustainTime": 205.23694352869435,
          "release": 116.80489563538069,
          "frequency": 198.9518623459392
        }
      },
      "fitness": 2.388508880744784,
      "pre_evaluation": 1.8563713120618857,
      "generation": 9,
      "chromosomeId": "651f3751-7260-40cf-a66a-3f59d1c76628"
    },
    {
      "fmParamsList": {
        "operator1": {
          "attack": 273.13305463703745,
          "decay": 251.2147202688809,
          "sustain": 204.35379165668363,
          "sustainTime": 325.91753280730984,
          "release": 333.1309146711569,
          "frequency": 157.97806707994826
        }
      },
      "fitness": 2.3885088807494146,
      "pre_evaluation": 1.8563713131088464,
      "generation": 9,
      "chromosomeId": "672df49c-263d-488e-a653-f81f5e7e3b62"
    },
    {
      "fmParamsList": {
        "operator1": {
          "attack": 194.81411790834784,
          "decay": 390.2691796019048,
          "sustain": 185.69339539375395,
          "sustainTime": 239.15416754422438,
          "release": 378.55902100389153,
          "frequency": 330.9641947367517
        }
      },
      "fitness": 2.388508880744784,
      "pre_evaluation": 1.8563714579222552,
      "generation": 9,
      "chromosomeId": "35b9bdd1-b83c-4774-9dec-0da43c4f9534"
    },
    {
      "fmParamsList": {
        "operator1": {
          "attack": 0,
          "decay": 500,
          "sustain": 248.26788297981952,
          "sustainTime": 439.1896782783316,
          "release": 349.7936367906917,
          "frequency": 442.0726829889995
        }
      },
      "fitness": 2.388508880744784,
      "pre_evaluation": 1.8563713120618857,
      "generation": 9,
      "chromosomeId": "74758283-c060-4377-b6a4-7154e5e2a9dc"
    },
    {
      "fmParamsList": {
        "operator1": {
          "attack": 192.86676398929916,
          "decay": 303.7939615766612,
          "sustain": 0,
          "sustainTime": 337.69097927249186,
          "release": 294.87663215727537,
          "frequency": 290.60163675768564
        }
      },
      "fitness": 2.388508880744784,
      "pre_evaluation": 1.8563713120618857,
      "generation": 9,
      "chromosomeId": "db47176d-d3e5-49c9-8b65-f1a039c17e34"
    },
    {
      "fmParamsList": {
        "operator1": {
          "attack": 195.95565100856504,
          "decay": 203.14351161439566,
          "sustain": 294.51608205105015,
          "sustainTime": 195.9246658868563,
          "release": 465.6350730228422,
          "frequency": 0
        }
      },
      "fitness": 2.388508880744784,
      "pre_evaluation": 1.8563713120618857,
      "generation": 9,
      "chromosomeId": "88096bbe-f43f-4d40-b51b-6285ba3ce9ec"
    },
    {
      "fmParamsList": {
        "operator1": {
          "attack": 61.702584047984864,
          "decay": 325.2306414303601,
          "sustain": 304.7846602120462,
          "sustainTime": 41.214995043230516,
          "release": 308.0964677716423,
          "frequency": 247.30425995058346
        }
      },
      "fitness": 2.388508880744784,
      "pre_evaluation": 1.8563713120618857,
      "generation": 9,
      "chromosomeId": "2c704c8e-ca48-4d33-a4fa-4c1a5547f186"
    },
    {
      "fmParamsList": {
        "operator1": {
          "attack": 110.51162684397286,
          "decay": 312.1537040496421,
          "sustain": 352.0963903542078,
          "sustainTime": 230.91287291108404,
          "release": 500,
          "frequency": 29.069163360286637
        }
      },
      "fitness": 2.388508880744784,
      "pre_evaluation": 1.8563713120618894,
      "generation": 9,
      "chromosomeId": "57997de7-9025-431a-add5-abf5224e2810"
    },
    {
      "fmParamsList": {
        "operator1": {
          "attack": 251.89253168581405,
          "decay": 47.4496532103742,
          "sustain": 157.02017950773586,
          "sustainTime": 0,
          "release": 314.6727307223266,
          "frequency": 237.5824615118647
        }
      },
      "fitness": 2.388508880744784,
      "pre_evaluation": 1.8563713120618857,
      "generation": 9,
      "chromosomeId": "4114a1c6-4e98-4e57-bf0b-e450105f14ef"
    },
    {
      "fmParamsList": {
        "operator1": {
          "attack": 324.21701836855027,
          "decay": 274.721437241605,
          "sustain": 305.6279628870384,
          "sustainTime": 189.0873559026054,
          "release": 444.7705853752923,
          "frequency": 312.9421837777256
        }
      },
      "fitness": 2.388508880744784,
      "pre_evaluation": 1.8563713120618857,
      "generation": 9,
      "chromosomeId": "98477638-f03a-4e1c-9fd9-fc8e41d8d8e6"
    },
    {
      "fmParamsList": {
        "operator1": {
          "attack": 301.63310215998246,
          "decay": 265.03772519163437,
          "sustain": 318.1484698540341,
          "sustainTime": 267.39751450376224,
          "release": 326.7265759097239,
          "frequency": 282.2572077976142
        }
      },
      "fitness": 2.388508880744784,
      "pre_evaluation": 1.9652114257763396,
      "generation": 9,
      "chromosomeId": "afdb9a66-b5f0-4228-be4f-44502b250a8a"
    },
    {
      "fmParamsList": {
        "operator1": {
          "attack": 483.3984170478826,
          "decay": 262.4754439591755,
          "sustain": 328.153488869764,
          "sustainTime": 438.13339630855273,
          "release": 150.95282473976792,
          "frequency": 340.3377344005176
        }
      },
      "fitness": 2.388508880744784,
      "pre_evaluation": 1.8563713120618857,
      "generation": 9,
      "chromosomeId": "a22cda8b-9ce4-4eb9-9a7c-83b0fcfdb31a"
    },
    {
      "fmParamsList": {
        "operator1": {
          "attack": 193.40921786892142,
          "decay": 169.77382965565045,
          "sustain": 500,
          "sustainTime": 246.75393789803394,
          "release": 294.723901882017,
          "frequency": 245.2202615102648
        }
      },
      "fitness": 2.388508880744784,
      "pre_evaluation": 1.8563730456874319,
      "generation": 9,
      "chromosomeId": "8684d13a-697f-4168-94c3-51e388d2db75"
    },
    {
      "fmParamsList": {
        "operator1": {
          "attack": 268.3968642128733,
          "decay": 250.32356641759338,
          "sustain": 275.6422805230894,
          "sustainTime": 500,
          "release": 334.9903375418893,
          "frequency": 198.64242039108063
        }
      },
      "fitness": 2.388508880744784,
      "pre_evaluation": 1.8563713120618857,
      "generation": 9,
      "chromosomeId": "944db644-95f1-4895-b2ba-14aa2113f827"
    },
    {
      "fmParamsList": {
        "operator1": {
          "attack": 51.76480657499435,
          "decay": 238.96309969690367,
          "sustain": 104.56212387179288,
          "sustainTime": 257.1104307318504,
          "release": 216.42439444636292,
          "frequency": 175.3111365378415
        }
      },
      "fitness": 2.3885100306877876,
      "pre_evaluation": 1.8563713424008077,
      "generation": 9,
      "chromosomeId": "6948d22e-e588-4e08-b28a-e457c18d9ca8"
    },
    {
      "fmParamsList": {
        "operator1": {
          "attack": 172.2480703071838,
          "decay": 2.076906643069032,
          "sustain": 112.54523912370566,
          "sustainTime": 270.7970773096306,
          "release": 307.636411597241,
          "frequency": 211.31406598687653
        }
      },
      "fitness": 2.388508880744784,
      "pre_evaluation": 1.856371490071155,
      "generation": 9,
      "chromosomeId": "2532c4b4-9c6a-4a69-8a7e-6e79cbbba031"
    },
    {
      "fmParamsList": {
        "operator1": {
          "attack": 346.7336497386866,
          "decay": 253.52783820910295,
          "sustain": 292.31441105430554,
          "sustainTime": 362.4621634513379,
          "release": 486.5165801676431,
          "frequency": 0
        }
      },
      "fitness": 2.388508880744784,
      "pre_evaluation": 1.8563713120618857,
      "generation": 9,
      "chromosomeId": "27eb9115-b495-411b-86a9-b5c83e5051eb"
    },
    {
      "fmParamsList": {
        "operator1": {
          "attack": 303.14316497121087,
          "decay": 284.90581742624954,
          "sustain": 304.3897478067277,
          "sustainTime": 243.86553801103517,
          "release": 167.50661132132942,
          "frequency": 20.01767587642145
        }
      },
      "fitness": 2.388508880744784,
      "pre_evaluation": 1.85637131241662,
      "generation": 9,
      "chromosomeId": "f1e01729-fbe3-46c5-8c78-9f9c9eca985f"
    },
    {
      "fmParamsList": {
        "operator1": {
          "attack": 22.385843618857088,
          "decay": 403.68925964522566,
          "sustain": 360.1603970019119,
          "sustainTime": 350.6753081378595,
          "release": 326.27343767639746,
          "frequency": 127.19007618218227
        }
      },
      "fitness": 2.388508880744784,
      "pre_evaluation": 1.8563713120618857,
      "generation": 9,
      "chromosomeId": "c006ed01-434e-4414-a485-397a77259814"
    },
    {
      "fmParamsList": {
        "operator1": {
          "attack": 184.04564018128409,
          "decay": 48.77354061149114,
          "sustain": 396.4995426938728,
          "sustainTime": 383.82818580142657,
          "release": 231.94684109277046,
          "frequency": 323.22551428928665
        }
      },
      "fitness": 2.388508880744784,
      "pre_evaluation": 1.8563713120618857,
      "generation": 9,
      "chromosomeId": "304ea87c-310b-44f3-8e6f-68ac5c7f5d0c"
    },
    {
      "fmParamsList": {
        "operator1": {
          "attack": 218.84061636814067,
          "decay": 316.4546315537943,
          "sustain": 316.4346363167457,
          "sustainTime": 209.42747406306438,
          "release": 387.35446442399723,
          "frequency": 57.757527564032074
        }
      },
      "fitness": 2.388508880744784,
      "pre_evaluation": 1.856371312061886,
      "generation": 9,
      "chromosomeId": "01232922-180d-404d-9b65-f318a1da7080"
    },
    {
      "fmParamsList": {
        "operator1": {
          "attack": 0,
          "decay": 235.31456194157866,
          "sustain": 286.0308830031714,
          "sustainTime": 303.3874616058365,
          "release": 142.90175282866136,
          "frequency": 300.74184682325864
        }
      },
      "fitness": 2.388508965641178,
      "pre_evaluation": 1.8563714045477226,
      "generation": 9,
      "chromosomeId": "08345a03-5194-43e5-a6d0-ce52668fd4e6"
    },
    {
      "fmParamsList": {
        "operator1": {
          "attack": 83.6920663757396,
          "decay": 438.83795088690795,
          "sustain": 381.8498223920636,
          "sustainTime": 230.52118133962722,
          "release": 425.8652280252968,
          "frequency": 271.27175944788945
        }
      },
      "fitness": 2.388508880744784,
      "pre_evaluation": 1.8563713126759462,
      "generation": 9,
      "chromosomeId": "db18b12b-7b0f-4b84-be71-877a61657c1b"
    },
    {
      "fmParamsList": {
        "operator1": {
          "attack": 339.1291129668982,
          "decay": 253.7112286307617,
          "sustain": 336.0023218487508,
          "sustainTime": 284.46727213016686,
          "release": 329.4123071740414,
          "frequency": 350.37417797395136
        }
      },
      "fitness": 2.388508880744784,
      "pre_evaluation": 1.8623422585035445,
      "generation": 9,
      "chromosomeId": "e1109ca8-db0f-41a8-9ee8-4a6755b4f015"
    },
    {
      "fmParamsList": {
        "operator1": {
          "attack": 26.448256898145857,
          "decay": 287.58143549914047,
          "sustain": 334.738317531884,
          "sustainTime": 206.89349107713582,
          "release": 266.55163035738667,
          "frequency": 322.09637491589774
        }
      },
      "fitness": 2.388508880744784,
      "pre_evaluation": 1.8563713120618925,
      "generation": 9,
      "chromosomeId": "b77bd7b1-8afd-4c41-9724-3e5e9495c4c2"
    },
    {
      "fmParamsList": {
        "operator1": {
          "attack": 341.0263996870658,
          "decay": 419.0817128279657,
          "sustain": 264.1616725607689,
          "sustainTime": 310.90857930677237,
          "release": 162.97398419061358,
          "frequency": 229.81563635352427
        }
      },
      "fitness": 2.388508880744784,
      "pre_evaluation": 1.8563713202404704,
      "generation": 9,
      "chromosomeId": "19e33fca-0d2a-424a-9089-5e8f2744b691"
    },
    {
      "fmParamsList": {
        "operator1": {
          "attack": 440.89114793106353,
          "decay": 242.85363986566148,
          "sustain": 467.81092781965305,
          "sustainTime": 330.6647439684275,
          "release": 17.94608920327775,
          "frequency": 500
        }
      },
      "fitness": 2.388508880744784,
      "pre_evaluation": 1.8563713120618857,
      "generation": 9,
      "chromosomeId": "889a0db9-f78e-4d8d-ad4e-9cb2920d270f"
    },
    {
      "fmParamsList": {
        "operator1": {
          "attack": 115.20755574921361,
          "decay": 181.93992172986236,
          "sustain": 500,
          "sustainTime": 330.4016655249126,
          "release": 187.889521240107,
          "frequency": 127.15680079864094
        }
      },
      "fitness": 2.388508880744784,
      "pre_evaluation": 1.8563713120618919,
      "generation": 9,
      "chromosomeId": "a9547cd0-5f06-4876-822b-573051cc2714"
    },
    {
      "fmParamsList": {
        "operator1": {
          "attack": 204.70068684296993,
          "decay": 318.4764527425022,
          "sustain": 347.9891665742383,
          "sustainTime": 315.7677831177903,
          "release": 145.9739661099318,
          "frequency": 257.4356943902387
        }
      },
      "fitness": 2.388508880744784,
      "pre_evaluation": 1.8563713611070958,
      "generation": 9,
      "chromosomeId": "a5b7bf4b-70c1-479a-837e-b4b5ea4d64c2"
    },
    {
      "fmParamsList": {
        "operator1": {
          "attack": 329.50490329246435,
          "decay": 259.4164677290015,
          "sustain": 272.8009910400037,
          "sustainTime": 329.2498718869567,
          "release": 303.1360675758597,
          "frequency": 220.51992144903923
        }
      },
      "fitness": 2.388508880744784,
      "pre_evaluation": 1.8563713133210769,
      "generation": 9,
      "chromosomeId": "b32e6c11-d048-4899-8722-6d4b15d919c9"
    },
    {
      "fmParamsList": {
        "operator1": {
          "attack": 371.90719349460244,
          "decay": 283.62192855514013,
          "sustain": 303.0200995311932,
          "sustainTime": 442.2493444157851,
          "release": 239.83790652215492,
          "frequency": 305.18249515283094
        }
      },
      "fitness": 2.388508880744784,
      "pre_evaluation": 1.8563713120618857,
      "generation": 9,
      "chromosomeId": "fc75f820-7a9b-4843-a163-63cd5b8c479e"
    },
    {
      "fmParamsList": {
        "operator1": {
          "attack": 354.15929157910267,
          "decay": 88.55808383215718,
          "sustain": 351.3097617856289,
          "sustainTime": 280.73691950011,
          "release": 470.4071103009947,
          "frequency": 170.45879065039878
        }
      },
      "fitness": 2.388508880744784,
      "pre_evaluation": 1.8563713515108238,
      "generation": 9,
      "chromosomeId": "eeef8fed-3a9b-4be3-a378-16a1656f2b98"
    },
    {
      "fmParamsList": {
        "operator1": {
          "attack": 302.14235338269515,
          "decay": 446.8945867305195,
          "sustain": 275.98387926555233,
          "sustainTime": 284.3466333226022,
          "release": 411.313870542473,
          "frequency": 339.73035333540406
        }
      },
      "fitness": 2.388508880744784,
      "pre_evaluation": 1.8564345709763703,
      "generation": 9,
      "chromosomeId": "70d4a909-77b8-4285-b715-7d113c8c9d61"
    },
    {
      "fmParamsList": {
        "operator1": {
          "attack": 234.89102283000682,
          "decay": 275.61011939056215,
          "sustain": 317.28586703808304,
          "sustainTime": 220.0703683840155,
          "release": 300.5579070550467,
          "frequency": 263.3173620056583
        }
      },
      "fitness": 2.388508880744784,
      "pre_evaluation": 1.8563713175570709,
      "generation": 9,
      "chromosomeId": "b63f9299-0330-4ced-8606-61c1c7da6ac4"
    },
    {
      "fmParamsList": {
        "operator1": {
          "attack": 236.71388226612117,
          "decay": 231.86035387876598,
          "sustain": 238.09419414842193,
          "sustainTime": 235.16497080402561,
          "release": 331.87302668883797,
          "frequency": 278.73511443413463
        }
      },
      "fitness": 2.390389037681027,
      "pre_evaluation": 1.856376675518553,
      "generation": 9,
      "chromosomeId": "38477abc-1d1f-436a-a588-a3fc78f99c53"
    },
    {
      "fmParamsList": {
        "operator1": {
          "attack": 133.57346772199753,
          "decay": 287.630346044031,
          "sustain": 317.91099019257297,
          "sustainTime": 239.6095635264186,
          "release": 228.07293378021018,
          "frequency": 248.8184199592905
        }
      },
      "fitness": 2.388508880744784,
      "pre_evaluation": 1.8564717264924462,
      "generation": 9,
      "chromosomeId": "6ec548b8-6636-4eb5-ae8d-e599999168e5"
    },
    {
      "fmParamsList": {
        "operator1": {
          "attack": 168.9352014871884,
          "decay": 402.67808224203554,
          "sustain": 320.04988376158997,
          "sustainTime": 303.9900642298174,
          "release": 42.0649632311443,
          "frequency": 384.59396655366896
        }
      },
      "fitness": 2.388508880744784,
      "pre_evaluation": 1.8563713120621683,
      "generation": 9,
      "chromosomeId": "0280b8eb-f581-44c6-9cbc-0aff00e578a8"
    },
    {
      "fmParamsList": {
        "operator1": {
          "attack": 292.62775415588226,
          "decay": 302.051033342718,
          "sustain": 161.71022104644584,
          "sustainTime": 251.67962787326775,
          "release": 216.79435306494224,
          "frequency": 500
        }
      },
      "fitness": 2.388508880744784,
      "pre_evaluation": 1.8563713123113479,
      "generation": 9,
      "chromosomeId": "3d9a65d6-5c14-484b-b59d-7ff2881837fc"
    },
    {
      "fmParamsList": {
        "operator1": {
          "attack": 220.7895182128382,
          "decay": 305.41872366950196,
          "sustain": 328.30965495347255,
          "sustainTime": 387.12433456089997,
          "release": 356.12332270290176,
          "frequency": 368.4883456894766
        }
      },
      "fitness": 2.388508880744784,
      "pre_evaluation": 1.8563713120618857,
      "generation": 9,
      "chromosomeId": "c910b58f-734b-43f9-a9a2-bbcae808f833"
    },
    {
      "fmParamsList": {
        "operator1": {
          "attack": 294.5962110638286,
          "decay": 437.25156155286845,
          "sustain": 285.3016212237208,
          "sustainTime": 250.7050850342675,
          "release": 199.29741123967784,
          "frequency": 289.0977910365424
        }
      },
      "fitness": 2.388508880744784,
      "pre_evaluation": 1.8563928501381322,
      "generation": 9,
      "chromosomeId": "6f47b76d-c962-4b9a-986c-7d52143b4619"
    },
    {
      "fmParamsList": {
        "operator1": {
          "attack": 101.84012389950212,
          "decay": 310.7971183352119,
          "sustain": 321.42152860027943,
          "sustainTime": 215.0774205008812,
          "release": 424.3475255545463,
          "frequency": 470.12717298339584
        }
      },
      "fitness": 2.388508880744784,
      "pre_evaluation": 1.8563713120618863,
      "generation": 9,
      "chromosomeId": "5e7aa3f1-b2ee-472b-99c2-110d948b260e"
    },
    {
      "fmParamsList": {
        "operator1": {
          "attack": 494.53090908226955,
          "decay": 212.31140892050797,
          "sustain": 142.31419146199997,
          "sustainTime": 194.02209138890439,
          "release": 500,
          "frequency": 226.1961696301441
        }
      },
      "fitness": 2.388508880744784,
      "pre_evaluation": 1.8563713120618857,
      "generation": 9,
      "chromosomeId": "6ac2fe6e-2789-41d7-99b0-cb1606ae8d99"
    },
    {
      "fmParamsList": {
        "operator1": {
          "attack": 289.5872079240348,
          "decay": 41.97444369121288,
          "sustain": 131.95434033941763,
          "sustainTime": 317.60149131472497,
          "release": 340.5630399170733,
          "frequency": 273.56556482713694
        }
      },
      "fitness": 2.388508880744784,
      "pre_evaluation": 1.8563713120808187,
      "generation": 9,
      "chromosomeId": "83b17654-af44-4b15-8118-ce08f8ff8be5"
    },
    {
      "fmParamsList": {
        "operator1": {
          "attack": 381.34951574974485,
          "decay": 167.74387507289705,
          "sustain": 481.28314956931433,
          "sustainTime": 184.53693659999465,
          "release": 312.71942337783037,
          "frequency": 313.5494823764665
        }
      },
      "fitness": 2.388508880744784,
      "pre_evaluation": 1.8563713120618857,
      "generation": 9,
      "chromosomeId": "603826ad-1012-4a81-a881-d1f6ea40ff33"
    },
    {
      "fmParamsList": {
        "operator1": {
          "attack": 145.39905292319804,
          "decay": 213.57292089353206,
          "sustain": 302.8194202596104,
          "sustainTime": 294.1712345346721,
          "release": 235.93821375713955,
          "frequency": 246.63235100949944
        }
      },
      "fitness": 2.388508880744784,
      "pre_evaluation": 1.9080358182436015,
      "generation": 9,
      "chromosomeId": "c8f1779d-3994-4586-ab3a-4042ee9dc992"
    },
    {
      "fmParamsList": {
        "operator1": {
          "attack": 446.7723120369739,
          "decay": 259.6229326074462,
          "sustain": 122.72911094278422,
          "sustainTime": 353.55852429275353,
          "release": 397.14151897962853,
          "frequency": 234.9327517282656
        }
      },
      "fitness": 2.388508880744784,
      "pre_evaluation": 1.8563713120618857,
      "generation": 9,
      "chromosomeId": "6d1686e2-616e-4d81-bb73-70655fcf3831"
    },
    {
      "fmParamsList": {
        "operator1": {
          "attack": 267.0464713432677,
          "decay": 248.02775234413912,
          "sustain": 411.20354986298275,
          "sustainTime": 245.1665621784146,
          "release": 141.80356010391273,
          "frequency": 195.5051533033365
        }
      },
      "fitness": 2.3885090528553787,
      "pre_evaluation": 1.8563713670755335,
      "generation": 9,
      "chromosomeId": "a48a41be-2e8e-4c07-80ad-b381afd79f4e"
    },
    {
      "fmParamsList": {
        "operator1": {
          "attack": 246.44580620342015,
          "decay": 299.0873229100119,
          "sustain": 263.4883233939583,
          "sustainTime": 382.6828697904878,
          "release": 335.95441088597414,
          "frequency": 308.4204049885789
        }
      },
      "fitness": 2.388508880744784,
      "pre_evaluation": 1.8563713120618857,
      "generation": 9,
      "chromosomeId": "dd7332f8-b0df-40da-aeb8-04251e30dfd2"
    },
    {
      "fmParamsList": {
        "operator1": {
          "attack": 348.49213041480516,
          "decay": 248.9868787659194,
          "sustain": 248.27879550420067,
          "sustainTime": 319.94551655509656,
          "release": 454.3336887801131,
          "frequency": 220.75011024900164
        }
      },
      "fitness": 2.388509152249393,
      "pre_evaluation": 1.8563713120958723,
      "generation": 9,
      "chromosomeId": "55eb4061-9e12-4db5-af53-3bd5f3218cc2"
    },
    {
      "fmParamsList": {
        "operator1": {
          "attack": 323.1475137111121,
          "decay": 171.67468788520364,
          "sustain": 500,
          "sustainTime": 362.20590501203327,
          "release": 285.79947838676196,
          "frequency": 202.99195477389054
        }
      },
      "fitness": 2.388508880744784,
      "pre_evaluation": 1.8563713120618857,
      "generation": 9,
      "chromosomeId": "32b476c0-a8a9-4dae-a4a3-5283d2420175"
    },
    {
      "fmParamsList": {
        "operator1": {
          "attack": 273.65761017428105,
          "decay": 124.6857658820087,
          "sustain": 280.2697821486706,
          "sustainTime": 353.9080015871598,
          "release": 72.89328379628554,
          "frequency": 376.1231267127966
        }
      },
      "fitness": 2.388508880744784,
      "pre_evaluation": 1.8563713120618857,
      "generation": 9,
      "chromosomeId": "fa5e64aa-295a-47ed-b461-dfb4c92e0db3"
    },
    {
      "fmParamsList": {
        "operator1": {
          "attack": 229.17938586604976,
          "decay": 367.687464955439,
          "sustain": 285.38539751633715,
          "sustainTime": 311.83883707520397,
          "release": 319.47324748181495,
          "frequency": 203.39889675321035
        }
      },
      "fitness": 2.388508880744784,
      "pre_evaluation": 1.8565053758756094,
      "generation": 9,
      "chromosomeId": "2f8d1067-1eae-4715-94cf-a1be10a6517b"
    },
    {
      "fmParamsList": {
        "operator1": {
          "attack": 327.73636263096085,
          "decay": 315.8601467271444,
          "sustain": 317.93928831374103,
          "sustainTime": 386.58679451600847,
          "release": 453.4635729907907,
          "frequency": 258.23710464782977
        }
      },
      "fitness": 2.388508880744784,
      "pre_evaluation": 1.8563713120618857,
      "generation": 9,
      "chromosomeId": "3c462b5f-d28a-44e6-adad-54f729cb984f"
    },
    {
      "fmParamsList": {
        "operator1": {
          "attack": 299.0939649978095,
          "decay": 459.3638403922331,
          "sustain": 347.85391378708454,
          "sustainTime": 407.732025340513,
          "release": 153.78164507362277,
          "frequency": 289.4704212253167
        }
      },
      "fitness": 2.388508880744784,
      "pre_evaluation": 1.8563713120618857,
      "generation": 9,
      "chromosomeId": "55a6a41c-9027-47a8-956b-dba185f0933d"
    },
    {
      "fmParamsList": {
        "operator1": {
          "attack": 274.92448286246025,
          "decay": 248.0074053262523,
          "sustain": 306.2658260047084,
          "sustainTime": 279.3334375410244,
          "release": 330.96143143290936,
          "frequency": 252.87701790110998
        }
      },
      "fitness": 2.3885565177708648,
      "pre_evaluation": 2.206112276752652,
      "generation": 9,
      "chromosomeId": "478fd8e0-fdff-4e59-85f9-7bb4cda026e6"
    },
    {
      "fmParamsList": {
        "operator1": {
          "attack": 75.12205176491068,
          "decay": 221.67802245922917,
          "sustain": 164.0008242063329,
          "sustainTime": 312.40464941352207,
          "release": 208.93746790046268,
          "frequency": 71.14889549967853
        }
      },
      "fitness": 2.388508880744784,
      "pre_evaluation": 1.8563713123074306,
      "generation": 9,
      "chromosomeId": "520ae928-2b6f-48e2-98c1-787cc915a5e9"
    },
    {
      "fmParamsList": {
        "operator1": {
          "attack": 356.9543270699247,
          "decay": 282.60814580762803,
          "sustain": 320.83400211602685,
          "sustainTime": 370.62895543742286,
          "release": 40.37777608657612,
          "frequency": 257.57328211031404
        }
      },
      "fitness": 2.388508880744784,
      "pre_evaluation": 1.8563713120618857,
      "generation": 9,
      "chromosomeId": "230c714e-8a65-4732-ae94-f422f5ea1bdb"
    },
    {
      "fmParamsList": {
        "operator1": {
          "attack": 340.736513735764,
          "decay": 104.79327783202999,
          "sustain": 499.9174797649874,
          "sustainTime": 0,
          "release": 221.13097446781282,
          "frequency": 260.5398637381622
        }
      },
      "fitness": 2.388508880744784,
      "pre_evaluation": 1.8563713120618857,
      "generation": 9,
      "chromosomeId": "fd769262-a092-41a3-8964-a4f43f31d074"
    },
    {
      "fmParamsList": {
        "operator1": {
          "attack": 3.973449231071008,
          "decay": 259.35699079808484,
          "sustain": 307.60677837280707,
          "sustainTime": 255.5416267757277,
          "release": 229.5422125101373,
          "frequency": 283.6888532097678
        }
      },
      "fitness": 2.388508880744784,
      "pre_evaluation": 1.8570601236012485,
      "generation": 9,
      "chromosomeId": "6d463e5e-8f88-4332-9655-cd7ba85b27c8"
    },
    {
      "fmParamsList": {
        "operator1": {
          "attack": 242.9150361324109,
          "decay": 225.73100490113188,
          "sustain": 336.98645255422633,
          "sustainTime": 419.34113135288493,
          "release": 337.74528292432626,
          "frequency": 252.24171004584423
        }
      },
      "fitness": 2.3885088807511874,
      "pre_evaluation": 1.8563713120618857,
      "generation": 9,
      "chromosomeId": "eb66d4fa-622d-4e49-a933-3f8cf6138660"
    },
    {
      "fmParamsList": {
        "operator1": {
          "attack": 260.9755387635348,
          "decay": 239.81976412936098,
          "sustain": 243.05879936440198,
          "sustainTime": 296.36375658710983,
          "release": 325.85853761450943,
          "frequency": 241.33046323251335
        }
      },
      "fitness": 3.2792502046210696,
      "pre_evaluation": 1.8682407776155747,
      "generation": 9,
      "chromosomeId": "5ee97d9d-603e-4e46-ad2d-05ad822d20c9"
    },
    {
      "fmParamsList": {
        "operator1": {
          "attack": 236.33907042504384,
          "decay": 404.32193513735626,
          "sustain": 241.4311542389367,
          "sustainTime": 0,
          "release": 315.47653446836165,
          "frequency": 224.96232949231185
        }
      },
      "fitness": 2.388508880744784,
      "pre_evaluation": 1.8563713120618857,
      "generation": 9,
      "chromosomeId": "8dc5c774-6f59-429b-8dc7-aa9b7cc8b81f"
    },
    {
      "fmParamsList": {
        "operator1": {
          "attack": 210.13863218114744,
          "decay": 185.6303268988577,
          "sustain": 260.9245688508652,
          "sustainTime": 397.2170083393994,
          "release": 210.01114150982255,
          "frequency": 301.3860667484305
        }
      },
      "fitness": 2.388508880744784,
      "pre_evaluation": 1.8563713120618857,
      "generation": 9,
      "chromosomeId": "a23113cf-f8a0-4ac9-b551-268258af7460"
    },
    {
      "fmParamsList": {
        "operator1": {
          "attack": 473.9547276199088,
          "decay": 243.86173595826108,
          "sustain": 0,
          "sustainTime": 214.68399360976457,
          "release": 68.92515307834026,
          "frequency": 295.41898381357396
        }
      },
      "fitness": 2.388508880879925,
      "pre_evaluation": 1.8563713120618857,
      "generation": 9,
      "chromosomeId": "6163bc3e-4a08-4211-ab1b-4be9b1d1f1c1"
    }
  ]
}